README.md
setup.cfg
setup.py
google_images_download_jeng/__init__.py
google_images_download_jeng/google_images_download.py
google_images_download_jeng.egg-info/PKG-INFO
google_images_download_jeng.egg-info/SOURCES.txt
google_images_download_jeng.egg-info/dependency_links.txt
google_images_download_jeng.egg-info/top_level.txt