Metadata-Version: 2.1
Name: google-images-download-jeng
Version: 0.2.0
Summary: Download Google Image
Home-page: https://github.com/tsjeng45/google_images_download_jeng
Author: jeng
Author-email: tsjeng45@yahoo.com.tw
License: UNKNOWN
Keywords: google-images-download
Platform: UNKNOWN
Classifier: Programming Language :: Python :: 3
Classifier: License :: OSI Approved :: MIT License
